untwisted/__init__.py
untwisted/client.py
untwisted/core.py
untwisted/dispatcher.py
untwisted/errors.py
untwisted/event.py
untwisted/expect.py
untwisted/file_reader.py
untwisted/file_writer.py
untwisted/iputils.py
untwisted/job.py
untwisted/network.py
untwisted/server.py
untwisted/sock_reader.py
untwisted/sock_writer.py
untwisted/splits.py
untwisted/task.py
untwisted/timer.py
untwisted/tkinter.py
untwisted/tools.py
untwisted/waker.py
untwisted-3.2.3.dist-info/licenses/LICENSE
untwisted-3.2.3.dist-info/METADATA
untwisted-3.2.3.dist-info/WHEEL
untwisted-3.2.3.dist-info/top_level.txt
untwisted-3.2.3.dist-info/RECORD
