Metadata-Version: 2.4
Name: untwisted
Version: 3.2.3
Summary: A better hell of callbacks for asynchronous programming. Untwisted is an Event Driven Framework for Python.
Home-page: https://github.com/untwisted/untwisted
Download-URL: https://github.com/untwisted/untwisted/releases
Author: Iury O. G. Figueiredo
Author-email: last.src@gmail.com
Keywords: asynchronous,programming,untwisted,framework,networking,protocols,irc,requests
License-File: LICENSE
Dynamic: author
Dynamic: author-email
Dynamic: download-url
Dynamic: home-page
Dynamic: keywords
Dynamic: license-file
Dynamic: summary
